jadtparser/__init__.py
jadtparser/alias.py
jadtparser/operator.py
jadtparser/parser.py
jadtparser/type_converter.py
ja_date_parser-0.2.0.dist-info/LICENSE
ja_date_parser-0.2.0.dist-info/METADATA
ja_date_parser-0.2.0.dist-info/WHEEL
ja_date_parser-0.2.0.dist-info/top_level.txt
ja_date_parser-0.2.0.dist-info/RECORD
