Metadata-Version: 2.1
Name: ja-date-parser
Version: 0.2.0
Summary: Package which offers handling to Japanese date format strings.
Home-page: https://github.com/isuya1992/ja-date-parser
Author: isuya1992
License: MIT
Platform: UNKNOWN
License-File: LICENSE
Requires-Dist: python-dateutil (==2.8.2)
